ELITactive/ELITactive.py
ELITactive-0.2.3.dist-info/METADATA
ELITactive-0.2.3.dist-info/WHEEL
ELITactive-0.2.3.dist-info/top_level.txt
ELITactive-0.2.3.dist-info/RECORD
